jupyterhub_kubespawner_dev-0.8.1.dev0.dist-info/METADATA
jupyterhub_kubespawner_dev-0.8.1.dev0.dist-info/RECORD
jupyterhub_kubespawner_dev-0.8.1.dev0.dist-info/WHEEL
jupyterhub_kubespawner_dev-0.8.1.dev0.dist-info/top_level.txt
kubespawner/__init__.py
kubespawner/clients.py
kubespawner/objects.py
kubespawner/proxy.py
kubespawner/reflector.py
kubespawner/spawner.py
kubespawner/traitlets.py
kubespawner/utils.py
