Metadata-Version: 2.1
Name: jupyterhub-kubespawner-dev
Version: 0.8.1.dev0
Summary: JupyterHub Spawner targeting Kubernetes
Home-page: http://github.com/jupyterhub/kubespawner
Author: Yuvi Panda
Author-email: yuvipanda@gmail.com
License: BSD
Platform: UNKNOWN
Requires-Python: >=3.5
Requires-Dist: jupyterhub (>=0.8)
Requires-Dist: pyYAML
Requires-Dist: kubernetes (==6.*)
Requires-Dist: escapism
Requires-Dist: jinja2
Requires-Dist: async-generator (>=1.8)
